pytest_rich/__init__.py
pytest_rich/capture.py
pytest_rich/header.py
pytest_rich/plugin.py
pytest_rich/py.typed
pytest_rich/terminal.py
pytest_rich/traceback.py
pytest_rich-0.2.0.dist-info/LICENSE
pytest_rich-0.2.0.dist-info/METADATA
pytest_rich-0.2.0.dist-info/WHEEL
pytest_rich-0.2.0.dist-info/entry_points.txt
pytest_rich-0.2.0.dist-info/top_level.txt
pytest_rich-0.2.0.dist-info/RECORD
