Metadata-Version: 2.1
Name: pytest-rich
Version: 0.2.0
Summary: Leverage rich for richer test session output
Home-page: https://github.com/nicoddemus/pytest-rich
Author: Bruno Oliveira
Author-email: nicoddemus@gmail.com
Maintainer: Bruno Oliveira
Maintainer-email: nicoddemus@gmail.com
License: MIT
Classifier: Development Status :: 4 - Beta
Classifier: Framework :: Pytest
Classifier: Intended Audience :: Developers
Classifier: Topic :: Software Development :: Testing
Classifier: Programming Language :: Python
Classifier: Programming Language :: Python :: 3
Classifier: Programming Language :: Python :: 3.9
Classifier: Programming Language :: Python :: 3.10
Classifier: Programming Language :: Python :: 3.11
Classifier: Programming Language :: Python :: 3.12
Classifier: Programming Language :: Python :: 3.13
Classifier: Programming Language :: Python :: 3 :: Only
Classifier: Programming Language :: Python :: Implementation :: CPython
Classifier: Programming Language :: Python :: Implementation :: PyPy
Classifier: Operating System :: OS Independent
Classifier: License :: OSI Approved :: MIT License
Requires-Python: >=3.9
License-File: LICENSE
Requires-Dist: attrs
Requires-Dist: pytest>=7.0
Requires-Dist: rich
Provides-Extra: dev
Requires-Dist: black; extra == "dev"
Requires-Dist: flake8; extra == "dev"
Requires-Dist: freezegun; extra == "dev"
Requires-Dist: mypy; extra == "dev"
Requires-Dist: pre-commit; extra == "dev"
Requires-Dist: reorder-python-imports; extra == "dev"
Requires-Dist: tox; extra == "dev"
Requires-Dist: types-attrs; extra == "dev"
